rubox/__init__.py
rubox/client.py
rubox/dict_like.py
rubox/enums.py
rubox/filters.py
rubox/keyboard.py
rubox/message.py
rubox/state_manager.py
rubox-0.2.0.dist-info/METADATA
rubox-0.2.0.dist-info/WHEEL
rubox-0.2.0.dist-info/top_level.txt
rubox-0.2.0.dist-info/RECORD
